CHANGELOG.txt
LICENCE.txt
MANIFEST.in
README.txt
setup.py
Offline_install/CHANGELOG.txt
Offline_install/LICENCE.txt
Offline_install/README.txt
Offline_install/__init__.py
Offline_install/setup.py
Offline_install/synproc.egg-info/SOURCES.txt
Offline_install/synproc.egg-info/dependency_links.txt
Offline_install/synproc.egg-info/requires.txt
Offline_install/synproc.egg-info/top_level.txt
synproc/__init__.py
synproc.egg-info/PKG-INFO
synproc.egg-info/SOURCES.txt
synproc.egg-info/dependency_links.txt
synproc.egg-info/requires.txt
synproc.egg-info/top_level.txt