Metadata-Version: 2.1
Name: synproc
Version: 0.1.3
Summary: A SYN file converting tool
Home-page: UNKNOWN
Author: Abdelhadi Harrouz
Author-email: abdelhadiharrouz@outlook.com
License: MIT
Keywords: Meteorology
Platform: UNKNOWN
Classifier: Development Status :: 5 - Production/Stable
Classifier: Intended Audience :: Education
Classifier: License :: OSI Approved :: MIT License
Classifier: Programming Language :: Python :: 3
License-File: LICENCE.txt
